profetorch/__init__.py
profetorch/_nbdev.py
profetorch/core.py
profetorch/losses.py
profetorch/callbacks/__init__.py
profetorch/callbacks/callbacks.py
profetorch/data/__init__.py
profetorch/data/data.py
profetorch/model/__init__.py
profetorch/model/blocks.py
profetorch/model/model.py
profetorch-0.0.2.dist-info/LICENSE
profetorch-0.0.2.dist-info/METADATA
profetorch-0.0.2.dist-info/WHEEL
profetorch-0.0.2.dist-info/entry_points.txt
profetorch-0.0.2.dist-info/top_level.txt
profetorch-0.0.2.dist-info/RECORD
