Metadata-Version: 2.1
Name: profetorch
Version: 0.0.2
Summary: Time series prediction with fastai, pytorch and prophet
Home-page: https://github.com/sachinruk/profetorch
Author: Sachinthak Abeywardana
Author-email: sachinra@it.usyd.edu.au
License: Apache Software License 2.0
Keywords: Time Series,Machine Learning,Deep Learning
Platform: UNKNOWN
Classifier: Development Status :: 3 - Alpha
Classifier: Intended Audience :: Developers
Classifier: License :: OSI Approved :: Apache Software License
Classifier: Natural Language :: English
Classifier: Programming Language :: Python :: 3.6
Classifier: Programming Language :: Python :: 3.7
Classifier: Programming Language :: Python :: 3.8
Requires-Python: >=3.6
Requires-Dist: fastai
Requires-Dist: torch (>=1.2.0)
Requires-Dist: torchvision
Requires-Dist: matplotlib
Requires-Dist: pandas
Requires-Dist: scipy
